{"nodes": [{"id": "src_components_deleteuserbutton_tsx", "label": "DeleteUserButton.tsx", "file_type": "code", "source_file": "src\\components\\DeleteUserButton.tsx", "source_location": "L1"}, {"id": "deleteuserbutton_deleteuserbutton", "label": "DeleteUserButton()", "file_type": "code", "source_file": "src\\components\\DeleteUserButton.tsx", "source_location": "L7"}], "edges": [{"source": "src_components_deleteuserbutton_tsx", "target": "react", "relation": "imports_from", "confidence": "EXTRACTED", "source_file": "src\\components\\DeleteUserButton.tsx", "source_location": "L3", "weight": 1.0}, {"source": "src_components_deleteuserbutton_tsx", "target": "navigation", "relation": "imports_from", "confidence": "EXTRACTED", "source_file": "src\\components\\DeleteUserButton.tsx", "source_location": "L4", "weight": 1.0}, {"source": "src_components_deleteuserbutton_tsx", "target": "react_hot_toast", "relation": "imports_from", "confidence": "EXTRACTED", "source_file": "src\\components\\DeleteUserButton.tsx", "source_location": "L5", "weight": 1.0}, {"source": "src_components_deleteuserbutton_tsx", "target": "deleteuserbutton_deleteuserbutton", "relation": "contains", "confidence": "EXTRACTED", "source_file": "src\\components\\DeleteUserButton.tsx", "source_location": "L7", "weight": 1.0}], "raw_calls": [{"caller_nid": "deleteuserbutton_deleteuserbutton", "callee": "useRouter", "source_file": "src\\components\\DeleteUserButton.tsx", "source_location": "L8"}, {"caller_nid": "deleteuserbutton_deleteuserbutton", "callee": "useState", "source_file": "src\\components\\DeleteUserButton.tsx", "source_location": "L9"}]}